dns_resolver.py
python3_resolver-1.0.2.dist-info/LICENSE.txt
python3_resolver-1.0.2.dist-info/METADATA
python3_resolver-1.0.2.dist-info/WHEEL
python3_resolver-1.0.2.dist-info/top_level.txt
python3_resolver-1.0.2.dist-info/RECORD
