Metadata-Version: 2.1
Name: python3-resolver
Version: 1.0.2
Summary: Module to resolve A/AAAA DNS records
Home-page: https://github.com/superstes/python3-resolver
Author: René Rath
Author-email: contact@superstes.eu
Project-URL: Repository, https://github.com/superstes/python3-resolver
Project-URL: Bug Tracker, https://github.com/superstes/python3-resolver/issues
Classifier: Programming Language :: Python :: 3
Classifier: License :: OSI Approved :: GNU General Public License v3 (GPLv3)
Classifier: Operating System :: OS Independent
Requires-Python: >=3.3
License-File: LICENSE.txt
